nestedDive/__init__.py
nestedDive/getHighest.py
nestedDive/getHighestpoint.py
nestedDive/testingExt.py
nestedDive-0.3.2.dist-info/LICENCE
nestedDive-0.3.2.dist-info/METADATA
nestedDive-0.3.2.dist-info/WHEEL
nestedDive-0.3.2.dist-info/top_level.txt
nestedDive-0.3.2.dist-info/RECORD
